mv_dupes/__init__.py
mv_dupes/main.py
mv_dupes-0.1.0.dist-info/METADATA
mv_dupes-0.1.0.dist-info/WHEEL
mv_dupes-0.1.0.dist-info/entry_points.txt
mv_dupes-0.1.0.dist-info/licenses/LICENSE
mv_dupes-0.1.0.dist-info/RECORD
