Metadata-Version: 2.4
Name: mv-dupes
Version: 0.1.0
Summary: Moves all except oldest and most recent duplicate files (same SHA256) to a directory.
Project-URL: Homepage, https://github.com/JamesParrott/mv_dupes
Project-URL: Bug Tracker, https://github.com/JamesParrott/mv_dupes/issues
Author-email: James Parrott <james.parrott@proton.me>
License: 
License-File: LICENSE
Requires-Python: >=3.11
